odoo/addons/stock_picking_analytic/README.rst
odoo/addons/stock_picking_analytic/__init__.py
odoo/addons/stock_picking_analytic/__manifest__.py
odoo/addons/stock_picking_analytic/i18n/es.po
odoo/addons/stock_picking_analytic/i18n/it.po
odoo/addons/stock_picking_analytic/i18n/pt_BR.po
odoo/addons/stock_picking_analytic/i18n/stock_picking_analytic.pot
odoo/addons/stock_picking_analytic/models/__init__.py
odoo/addons/stock_picking_analytic/models/stock_picking.py
odoo/addons/stock_picking_analytic/readme/CONTRIBUTORS.md
odoo/addons/stock_picking_analytic/readme/DESCRIPTION.md
odoo/addons/stock_picking_analytic/static/description/icon.png
odoo/addons/stock_picking_analytic/static/description/index.html
odoo/addons/stock_picking_analytic/tests/__init__.py
odoo/addons/stock_picking_analytic/tests/test_picking_analytic_account.py
odoo/addons/stock_picking_analytic/views/stock_picking.xml
odoo_addon_stock_picking_analytic-17.0.1.0.0.12.dist-info/METADATA
odoo_addon_stock_picking_analytic-17.0.1.0.0.12.dist-info/WHEEL
odoo_addon_stock_picking_analytic-17.0.1.0.0.12.dist-info/top_level.txt
odoo_addon_stock_picking_analytic-17.0.1.0.0.12.dist-info/RECORD
